[
  {
    "i": 33900,
    "b": 58,
    "c": 6003,
    "r": 6003,
    "o": 3,
    "t": "Opdat niemand zou wankelen door deze verdrukkingen. Want gij weet immers zelf dat dit onze bestemming is:"
  },
  {
    "i": 33901,
    "b": 58,
    "c": 6003,
    "r": 6003,
    "o": 4,
    "t": "toen wij bij u waren, hebben wij u voorzegd dat wij verdrukkingen zouden ondergaan, en dat is ook geschied, zoals gij weet."
  },
  {
    "i": 33902,
    "b": 58,
    "c": 6003,
    "r": 6003,
    "o": 5,
    "t": "Daarom heb ik, het niet langer kunnende uithouden, hem gezonden om naar uw geloof te informeren. Mogelijk heeft de Verzoeker u reeds bekoord, en is onze arbeid tevergeefs geweest!"
  },
  {
    "i": 33903,
    "b": 58,
    "c": 6003,
    "r": 6003,
    "o": 6,
    "t": "Maar nu is Timotheüs van u tot ons teruggekeerd, en heeft ons goede tijdingen gebracht van uw geloof en uw liefde: hij zegt dat gij altijd een goede herinnering aan ons bewaart, en dat gij ernaar verlangt ons terug te zien, evenzeer als wij u."
  },
  {
    "i": 33904,
    "b": 58,
    "c": 6003,
    "r": 6003,
    "o": 7,
    "t": "Daarom, broeders, zijn wij door uw geloof getroost te midden van al onze angsten en verdrukkingen."
  },
  {
    "i": 33905,
    "b": 58,
    "c": 6003,
    "r": 6003,
    "o": 8,
    "t": "Nu herleven wij, nu gij standvastig staat in de Heer."
  },
  {
    "i": 33906,
    "b": 58,
    "c": 6003,
    "r": 6003,
    "o": 9,
    "t": "Hoe zouden wij God genoeg kunnen danken voor u, voor alle vreugde die gij ons verschaft voor het aangezicht van onze God?"
  },
  {
    "i": 33907,
    "b": 58,
    "c": 6003,
    "r": 6003,
    "o": 10,
    "t": "Nacht en dag bidden wij Hem, met groot aandrang, om uw aangezicht terug te zien en te kunnen aanvullen wat er nog aan uw geloof ontbreekt."
  },
  {
    "i": 33908,
    "b": 58,
    "c": 6003,
    "r": 6003,
    "o": 11,
    "t": "Moge God Zelf, onze Vader, en onze Heer Jezus onze weg naar u toe effenen."
  },
  {
    "i": 33909,
    "b": 58,
    "c": 6003,
    "r": 6003,
    "o": 12,
    "t": "En u, moge de Heer u doen groeien en overvloeien in de liefde die gij jegens elkander hebt en jegens allen, gelijk wijzelf jegens u:"
  },
  {
    "i": 33910,
    "b": 58,
    "c": 6003,
    "r": 6003,
    "o": 13,
    "t": "opdat Hij aldus uw harten onberispelijk zal versterken in heiligheid voor het aangezicht van God, onze Vader, bij de wederkomst van onze Heer Jezus met al Zijn heiligen."
  },
  {
    "i": 33911,
    "b": 58,
    "c": 6004,
    "r": 6004,
    "o": 1,
    "t": "Voorts dan, broeders, vragen en vermanen wij u in de Heer Jezus: gij hebt van ons geleerd hoe gij moet leven om God te behagen, en zo leeft gij reeds; maakt daarin nog vorderingen."
  },
  {
    "i": 33912,
    "b": 58,
    "c": 6004,
    "r": 6004,
    "o": 2,
    "t": "Gij weet immers welke voorschriften wij u gegeven hebben door de Heer Jezus."
  },
  {
    "i": 33913,
    "b": 58,
    "c": 6004,
    "r": 6004,
    "o": 3,
    "t": "Want dit is de wil van God: uw heiliging; dat gij u onthoudt van onkuisheid,"
  },
  {
    "i": 33914,
    "b": 58,
    "c": 6004,
    "r": 6004,
    "o": 4,
    "t": "dat ieder van u weet zijn eigen lichaam te gebruiken in heiligheid en eerbied,"
  },
  {
    "i": 33915,
    "b": 58,
    "c": 6004,
    "r": 6004,
    "o": 5,
    "t": "zonder zich te laten meeslepen door hartstocht, zoals de heidenen die God niet kennen;"
  },
  {
    "i": 33916,
    "b": 58,
    "c": 6004,
    "r": 6004,
    "o": 6,
    "t": "dat niemand in deze zaak zijn broeder verdringt of bedriegt. De Heer oefent wraak over dit alles, zoals wij u reeds gezegd en betuigd hebben."
  },
  {
    "i": 33917,
    "b": 58,
    "c": 6004,
    "r": 6004,
    "o": 7,
    "t": "Want God heeft ons niet geroepen tot onreinheid, maar tot heiliging."
  },
  {
    "i": 33918,
    "b": 58,
    "c": 6004,
    "r": 6004,
    "o": 8,
    "t": "Wie dit dus verwerpt, verwerpt niet een mens, maar God, Die u Zijn Heilige Geest heeft geschonken."
  },
  {
    "i": 33919,
    "b": 58,
    "c": 6004,
    "r": 6004,
    "o": 9,
    "t": "Wat de broederliefde betreft, hebt gij het niet nodig dat men u schrijft, want gij hebt zelf van God geleerd elkander lief te hebben,"
  },
  {
    "i": 33920,
    "b": 58,
    "c": 6004,
    "r": 6004,
    "o": 10,
    "t": "en dit doet gij ook jegens alle broeders in geheel Macedonië. Maar wij vermanen u, broeders, om daarin nog vorderingen te maken,"
  },
  {
    "i": 33921,
    "b": 58,
    "c": 6004,
    "r": 6004,
    "o": 11,
    "t": "door er uw eer in te stellen rustig te leven, uw eigen zaken te behartigen en met uw eigen handen te werken, zoals wij u bevolen hebben."
  },
  {
    "i": 33922,
    "b": 58,
    "c": 6004,
    "r": 6004,
    "o": 12,
    "t": "Zo zult gij een eerbaar leven leiden ten opzichte van hen die buiten staan, en zult gij niemand nodig hebben."
  },
  {
    "i": 33923,
    "b": 58,
    "c": 6004,
    "r": 6004,
    "o": 13,
    "t": "Doch wij willen niet, broeders, dat gij onwetend zijt aangaande hen die ontslapen zijn, opdat gij niet treurt zoals de anderen, die geen hoop hebben."
  },
  {
    "i": 33924,
    "b": 58,
    "c": 6004,
    "r": 6004,
    "o": 14,
    "t": "Want indien wij geloven dat Jezus gestorven en opgestaan is, dan zal God ook hen die in Jezus ontslapen zijn, met Hem meenemen."
  },
  {
    "i": 33925,
    "b": 58,
    "c": 6004,
    "r": 6004,
    "o": 15,
    "t": "Want dit zeggen wij u met een woord van de Heer. Wij, de levenden, die nog in leven zijn bij de wederkomst van de Heer, zullen de ontslapenen niet voorgaan."
  },
  {
    "i": 33926,
    "b": 58,
    "c": 6004,
    "r": 6004,
    "o": 16,
    "t": "Want de Heer Zelf zal met een geroep, met de stem van de aartsengel en met de bazuin van God neerdalen uit de hemel, en de doden die in Christus zijn, zullen eerst opstaan;"
  },
  {
    "i": 33927,
    "b": 58,
    "c": 6004,
    "r": 6004,
    "o": 17,
    "t": "daarna zullen wij, de levenden, die nog in leven zijn, tezamen met hen opgenomen worden op de wolken, de Heer tegemoet in de lucht. En zo zullen wij altijd met de Heer zijn."
  },
  {
    "i": 33928,
    "b": 58,
    "c": 6004,
    "r": 6004,
    "o": 18,
    "t": "Vertroost elkander dan met deze woorden."
  },
  {
    "i": 33929,
    "b": 58,
    "c": 6005,
    "r": 6005,
    "o": 1,
    "t": "Wat de tijden en gelegenheden betreft, broeders, hebt gij het niet nodig dat men u erover schrijft."
  },
  {
    "i": 33930,
    "b": 58,
    "c": 6005,
    "r": 6005,
    "o": 2,
    "t": "Want gij weet zelf heel goed dat de dag des Heren komt als een dief in de nacht."
  },
  {
    "i": 33931,
    "b": 58,
    "c": 6005,
    "r": 6005,
    "o": 3,
    "t": "Wanneer de mensen zeggen: Vrede en veiligheid! dan zal hen plotseling verderf overvallen, zoals de weeën een zwangere vrouw, en zij zullen er niet aan ontkomen."
  },
  {
    "i": 33932,
    "b": 58,
    "c": 6005,
    "r": 6005,
    "o": 4,
    "t": "Maar gij, broeders, zijt niet in de duisternis, zodat die dag u als een dief zou overvallen:"
  },
  {
    "i": 33933,
    "b": 58,
    "c": 6005,
    "r": 6005,
    "o": 5,
    "t": "gij zijt allen kinderen van het licht, kinderen van de dag. Wij zijn niet van de nacht, noch van de duisternis."
  },
  {
    "i": 33934,
    "b": 58,
    "c": 6005,
    "r": 6005,
    "o": 6,
    "t": "Laten wij dan niet slapen, zoals de anderen, maar laten wij waakzaam en nuchter zijn."
  },
  {
    "i": 33935,
    "b": 58,
    "c": 6005,
    "r": 6005,
    "o": 7,
    "t": "Want wie slapen, slapen 's nachts, en wie dronken zijn, zijn 's nachts dronken."
  },
  {
    "i": 33936,
    "b": 58,
    "c": 6005,
    "r": 6005,
    "o": 8,
    "t": "Maar laten wij, die van de dag zijn, nuchter zijn, bekleed met het borstharnas van geloof en liefde, met de helm van de hoop op zaligheid."
  },
  {
    "i": 33937,
    "b": 58,
    "c": 6005,
    "r": 6005,
    "o": 9,
    "t": "Want God heeft ons niet bestemd tot toorn, maar tot het verkrijgen van zaligheid door onze Heer Jezus Christus,"
  },
  {
    "i": 33938,
    "b": 58,
    "c": 6005,
    "r": 6005,
    "o": 10,
    "t": "Die voor ons gestorven is, opdat wij, hetzij wakende hetzij slapende, tezamen met Hem zouden leven."
  },
  {
    "i": 33939,
    "b": 58,
    "c": 6005,
    "r": 6005,
    "o": 11,
    "t": "Daarom, troost elkander en bouwt elkander op, zoals gij reeds doet."
  },
  {
    "i": 33940,
    "b": 58,
    "c": 6005,
    "r": 6005,
    "o": 12,
    "t": "Wij vragen u, broeders, dat gij hen erkent die zich onder u inspannen, die u in de Heer voorgaan en u terechtwijzen."
  },
  {
    "i": 33941,
    "b": 58,
    "c": 6005,
    "r": 6005,
    "o": 13,
    "t": "Hebt hen in liefde ten zeerste hoog om hun werk. Houdt vrede onder elkander."
  },
  {
    "i": 33942,
    "b": 58,
    "c": 6005,
    "r": 6005,
    "o": 14,
    "t": "Wij vermanen u, broeders, wijst de ongeregelden terecht, bemoedigt de kleinmoedigen, ondersteunt de zwakken, weest lankmoedig jegens allen."
  },
  {
    "i": 33943,
    "b": 58,
    "c": 6005,
    "r": 6005,
    "o": 15,
    "t": "Ziet toe dat niemand kwaad met kwaad vergeldt, maar jaagt altijd het goede na, hetzij onder elkander, hetzij jegens allen."
  },
  {
    "i": 33944,
    "b": 58,
    "c": 6005,
    "r": 6005,
    "o": 16,
    "t": "Verblijdt u altijd."
  },
  {
    "i": 33945,
    "b": 58,
    "c": 6005,
    "r": 6005,
    "o": 17,
    "t": "Bidt zonder ophouden."
  },
  {
    "i": 33946,
    "b": 58,
    "c": 6005,
    "r": 6005,
    "o": 18,
    "t": "Dankt God in alles, want dit is de wil van God in Christus Jezus voor u."
  },
  {
    "i": 33947,
    "b": 58,
    "c": 6005,
    "r": 6005,
    "o": 19,
    "t": "Dooft de Geest niet uit,"
  },
  {
    "i": 33948,
    "b": 58,
    "c": 6005,
    "r": 6005,
    "o": 20,
    "t": "acht de profetieën niet gering,"
  },
  {
    "i": 33949,
    "b": 58,
    "c": 6005,
    "r": 6005,
    "o": 21,
    "t": "maar beproeft alles; behoudt het goede."
  },
  {
    "i": 33950,
    "b": 58,
    "c": 6005,
    "r": 6005,
    "o": 22,
    "t": "Onthoudt u van alle vorm van kwaad."
  },
  {
    "i": 33951,
    "b": 58,
    "c": 6005,
    "r": 6005,
    "o": 23,
    "t": "Moge de God des vredes Zelf u geheel en al heiligen, en moge uw geest, ziel en lichaam geheel onberispelijk bewaard blijven tot de wederkomst van onze Heer Jezus Christus."
  },
  {
    "i": 33952,
    "b": 58,
    "c": 6005,
    "r": 6005,
    "o": 24,
    "t": "Hij is getrouw Die u roept, Die het ook zal doen."
  },
  {
    "i": 33953,
    "b": 58,
    "c": 6005,
    "r": 6005,
    "o": 25,
    "t": "Broeders, bidt ook voor ons."
  },
  {
    "i": 33954,
    "b": 58,
    "c": 6005,
    "r": 6005,
    "o": 26,
    "t": "Groet alle broeders met een heilige kus."
  },
  {
    "i": 33955,
    "b": 58,
    "c": 6005,
    "r": 6005,
    "o": 27,
    "t": "Ik bezweer u bij de Heer dat deze brief aan alle broeders wordt voorgelezen."
  },
  {
    "i": 33956,
    "b": 58,
    "c": 6005,
    "r": 6005,
    "o": 28,
    "t": "De genade van onze Heer Jezus Christus zij met u."
  },
  {
    "i": 33957,
    "b": 59,
    "c": 6101,
    "r": 6101,
    "o": 1,
    "t": "Paulus, Silvanus en Timotheüs, aan de gemeente van de Thessalonicenzen in God, onze Vader, en de Heer Jezus Christus:"
  },
  {
    "i": 33958,
    "b": 59,
    "c": 6101,
    "r": 6101,
    "o": 2,
    "t": "Genade zij u en vrede van God de Vader en de Heer Jezus Christus."
  },
  {
    "i": 33959,
    "b": 59,
    "c": 6101,
    "r": 6101,
    "o": 3,
    "t": "Wij moeten God altijd voor u danken, broeders, en dat is ook terecht, omdat uw geloof krachtig toeneemt en de liefde van ieder voor de anderen onder u allen groeit,"
  },
  {
    "i": 33960,
    "b": 59,
    "c": 6101,
    "r": 6101,
    "o": 4,
    "t": "zodat wij zelf over u roemen in de gemeenten van God, vanwege uw standvastigheid en uw geloof in alle vervolgingen en verdrukkingen die gij verdraagt."
  },
  {
    "i": 33961,
    "b": 59,
    "c": 6101,
    "r": 6101,
    "o": 5,
    "t": "Daardoor wordt het rechtvaardig oordeel van God openbaar, dat gij het Koninkrijk van God waardig bevonden zult worden, waarvoor gij ook lijdt."
  },
  {
    "i": 33962,
    "b": 59,
    "c": 6101,
    "r": 6101,
    "o": 6,
    "t": "Want het is rechtvaardig van God om aan hen die u verdrukken, verdrukking te vergelden,"
  },
  {
    "i": 33963,
    "b": 59,
    "c": 6101,
    "r": 6101,
    "o": 7,
    "t": "en aan u die verdrukt wordt, verlichting te geven tezamen met ons, wanneer de Heer Jezus geopenbaard zal worden vanuit de hemel met de engelen van Zijn kracht,"
  },
  {
    "i": 33964,
    "b": 59,
    "c": 6101,
    "r": 6101,
    "o": 8,
    "t": "in vlammend vuur, wraak oefenend over hen die God niet kennen en over hen die het Evangelie van onze Heer Jezus niet gehoorzamen."
  },
  {
    "i": 33965,
    "b": 59,
    "c": 6101,
    "r": 6101,
    "o": 9,
    "t": "Dezen zullen gestraft worden met een eeuwig verderf, weg van het aangezicht van de Heer en van de heerlijkheid van Zijn macht,"
  },
  {
    "i": 33966,
    "b": 59,
    "c": 6101,
    "r": 6101,
    "o": 10,
    "t": "wanneer Hij komt om verheerlijkt te worden in Zijn heiligen en bewonderd te worden in allen die geloofd hebben - en gij hebt ons getuigenis geloofd. Zo zal het zijn op die dag."
  },
  {
    "i": 33967,
    "b": 59,
    "c": 6101,
    "r": 6101,
    "o": 11,
    "t": "Daartoe bidden wij ook altijd voor u, opdat onze God u Zijn roeping waardig zal achten, en Hij door Zijn kracht elk voornemen tot het goede en elk werk van uw geloof tot volkomenheid zal brengen;"
  },
  {
    "i": 33968,
    "b": 59,
    "c": 6101,
    "r": 6101,
    "o": 12,
    "t": "opdat de Naam van onze Heer Jezus in u verheerlijkt zal worden, en gij in Hem, overeenkomstig de genade van onze God en van de Heer Jezus Christus."
  },
  {
    "i": 33969,
    "b": 59,
    "c": 6102,
    "r": 6102,
    "o": 1,
    "t": "Wij vragen u, broeders, aangaande de komst van onze Heer Jezus Christus en onze vereniging met Hem,"
  },
  {
    "i": 33970,
    "b": 59,
    "c": 6102,
    "r": 6102,
    "o": 2,
    "t": "dat gij u niet zo spoedig van uw verstand laat brengen of in beroering brengt, hetzij door een uiting van de Geest, hetzij door een woord, hetzij door een brief die van ons zou komen, alsof de dag van de Heer reeds aangebroken zou zijn."
  },
  {
    "i": 33971,
    "b": 59,
    "c": 6102,
    "r": 6102,
    "o": 3,
    "t": "Laat niemand u op welke manier dan ook misleiden. Want eerst moet de afval komen en de mens van de wetteloosheid geopenbaard worden, de zoon van het verderf,"
  },
  {
    "i": 33972,
    "b": 59,
    "c": 6102,
    "r": 6102,
    "o": 4,
    "t": "de tegenstander die zich verheft boven al wat God genoemd of aanbeden wordt, zodat hij als God in de tempel van God gaat zitten en zich voordoet als God."
  },
  {
    "i": 33973,
    "b": 59,
    "c": 6102,
    "r": 6102,
    "o": 5,
    "t": "Herinnert gij u niet dat ik u dit zei toen ik nog bij u was?"
  },
  {
    "i": 33974,
    "b": 59,
    "c": 6102,
    "r": 6102,
    "o": 6,
    "t": "En gij weet wat hem nu nog tegenhoudt, zodat hij pas op zijn tijd geopenbaard zal worden."
  },
  {
    "i": 33975,
    "b": 59,
    "c": 6102,
    "r": 6102,
    "o": 7,
    "t": "Want het geheimenis van de wetteloosheid is reeds werkzaam. Alleen moet hij die hem nu nog tegenhoudt, uit de weg geruimd worden."
  },
  {
    "i": 33976,
    "b": 59,
    "c": 6102,
    "r": 6102,
    "o": 8,
    "t": "En dan zal de wetteloze geopenbaard worden, die de Heer zal doden door de adem van Zijn mond en tenietdoen door de verschijning van Zijn komst."
  },
  {
    "i": 33977,
    "b": 59,
    "c": 6102,
    "r": 6102,
    "o": 9,
    "t": "Zijn komst zal zijn naar de werking van de satan, met allerlei kracht, tekenen en bedrieglijke wonderen,"
  },
  {
    "i": 33978,
    "b": 59,
    "c": 6102,
    "r": 6102,
    "o": 10,
    "t": "en met allerlei misleiding van de ongerechtigheid in hen die verloren gaan, omdat zij de liefde tot de waarheid niet hebben aangenomen om zalig te worden."
  },
  {
    "i": 33979,
    "b": 59,
    "c": 6102,
    "r": 6102,
    "o": 11,
    "t": "Daarom zendt God hun een krachtige dwaling, zodat zij de leugen geloven,"
  },
  {
    "i": 33980,
    "b": 59,
    "c": 6102,
    "r": 6102,
    "o": 12,
    "t": "opdat zij allen veroordeeld worden, die de waarheid niet hebben geloofd, maar een welbehagen hebben gehad in de ongerechtigheid."
  },
  {
    "i": 33981,
    "b": 59,
    "c": 6102,
    "r": 6102,
    "o": 13,
    "t": "Maar wij zijn schuldig God altijd voor u te danken, broeders, die door de Heer bemind worden, omdat God u van het begin verkoren heeft tot zaligheid, in heiligmaking des Geestes en geloof der waarheid:"
  },
  {
    "i": 33982,
    "b": 59,
    "c": 6102,
    "r": 6102,
    "o": 14,
    "t": "waartoe Hij u ook geroepen heeft door ons Evangelie, tot de verkrijging van de heerlijkheid van onze Heere Jezus Christus."
  },
  {
    "i": 33983,
    "b": 59,
    "c": 6102,
    "r": 6102,
    "o": 15,
    "t": "Zo dan, broeders, staat vast en houdt de overleveringen, die u geleerd zijn, hetzij door ons woord, hetzij door onze brief."
  },
  {
    "i": 33984,
    "b": 59,
    "c": 6102,
    "r": 6102,
    "o": 16,
    "t": "En onze Heere Jezus Christus Zelf, en God, onze Vader, Die ons heeft liefgehad en ons een eeuwige troost en goede hoop gegeven heeft in genade,"
  },
  {
    "i": 33985,
    "b": 59,
    "c": 6102,
    "r": 6102,
    "o": 17,
    "t": "moge uw harten vertroosten en u bevestigen in alle goed werk en woord."
  },
  {
    "i": 33986,
    "b": 59,
    "c": 6103,
    "r": 6103,
    "o": 1,
    "t": "Voorts, broeders, bidt voor ons, opdat het Woord des Heeren zijn loop hebbe en verheerlijkt worde, gelijk ook bij u,"
  },
  {
    "i": 33987,
    "b": 59,
    "c": 6103,
    "r": 6103,
    "o": 2,
    "t": "en dat wij verlost mogen worden van de ongerechtige en boze mensen; want het geloof is niet aller deel."
  },
  {
    "i": 33988,
    "b": 59,
    "c": 6103,
    "r": 6103,
    "o": 3,
    "t": "Maar de Heere is getrouw, Die u zal bevestigen en bewaren voor de boze."
  },
  {
    "i": 33989,
    "b": 59,
    "c": 6103,
    "r": 6103,
    "o": 4,
    "t": "En wij betrouwen in de Heere van u, dat gij doet en zult doen, hetgeen wij u bevelen."
  },
  {
    "i": 33990,
    "b": 59,
    "c": 6103,
    "r": 6103,
    "o": 5,
    "t": "Doch de Heere bestiere uw harten tot de liefde van God en tot de lijdzaamheid van Christus."
  },
  {
    "i": 33991,
    "b": 59,
    "c": 6103,
    "r": 6103,
    "o": 6,
    "t": "Nu bevelen wij u, broeders, in de Naam van onze Heere Jezus Christus, dat gij u onttrekt van een iegelijk broeder die ongeregeld wandelt, en niet naar de overlevering die hij van ons ontvangen heeft."
  },
  {
    "i": 33992,
    "b": 59,
    "c": 6103,
    "r": 6103,
    "o": 7,
    "t": "Want gij weet zelf hoe gij ons behoort na te volgen; want wij hebben ons niet ongeregeld gedragen onder u,"
  },
  {
    "i": 33993,
    "b": 59,
    "c": 6103,
    "r": 6103,
    "o": 8,
    "t": "noch hebben wij van iemand brood voor niets gegeten, maar met arbeid en moeite hebben wij nacht en dag gewerkt, om niemand van u te verzwaren:"
  },
  {
    "i": 33994,
    "b": 59,
    "c": 6103,
    "r": 6103,
    "o": 9,
    "t": "niet alsof wij de macht niet hadden, maar om onszelf u tot een voorbeeld te stellen, opdat gij ons zoudt navolgen."
  },
  {
    "i": 33995,
    "b": 59,
    "c": 6103,
    "r": 6103,
    "o": 10,
    "t": "Want ook toen wij bij u waren, bevalen wij u dit: Indien iemand niet wil werken, die zal ook niet eten."
  },
  {
    "i": 33996,
    "b": 59,
    "c": 6103,
    "r": 6103,
    "o": 11,
    "t": "Want wij horen dat sommigen onder u ongeregeld wandelen, niet arbeidende, maar bezig zijnde met ydele dingen."
  },
  {
    "i": 33997,
    "b": 59,
    "c": 6103,
    "r": 6103,
    "o": 12,
    "t": "Zulken bevelen en vermanen wij door onze Heere Jezus Christus, dat zij, met stilheid werkende, hun eigen brood eten."
  },
  {
    "i": 33998,
    "b": 59,
    "c": 6103,
    "r": 6103,
    "o": 13,
    "t": "Maar gij, broeders, wordt niet moede wel te doen."
  },
  {
    "i": 33999,
    "b": 59,
    "c": 6103,
    "r": 6103,
    "o": 14,
    "t": "En indien iemand ons woord door deze brief niet gehoorzaam is, tekent dien aan, en vermengt u niet met hem, opdat hij beschaamd worde."
  }
]
